flajt/__init__.py
flajt-1.0.0.dist-info/METADATA
flajt-1.0.0.dist-info/RECORD
flajt-1.0.0.dist-info/WHEEL
flajt-1.0.0.dist-info/top_level.txt
